{
  "type": "Feature",
  "properties": {
    "iso:country":"KO",
    "name:kor_x_preferred":[
        "\ub2e8\ub300\ub3d9"
    ],
    "name:unk_x_variant":[
        "Dandae-dong",
        "\ub2e8\ub300\ub3d9"
    ],
    "qs:gn_fcode":"PPL",
    "qs:gn_local":0,
    "qs:gn_namadm1":"13",
    "qs:gn_name":"Tandae-dong",
    "qs:local_max":437,
    "qs:local_sum":826,
    "qs:localhoods":9,
    "qs:name":"\ub2e8\ub300\ub3d9",
    "qs:name_adm0":"\ud55c\uad6d",
    "qs:name_adm1":"\uacbd\uae30\ub3c4",
    "qs:name_adm2":"\uc131\ub0a8\uc2dc",
    "qs:name_lau":"\uc218\uc815\uad6c",
    "qs:name_local":"\uc218\uc815\uad6c",
    "qs:photo_max":1,
    "qs:photo_sum":2,
    "qs:placetype":"Suburb",
    "qs:quad_count":2,
    "qs:woe_adm0":23424868,
    "qs:woe_adm1":2345969,
    "qs:woe_adm2":28289288,
    "qs:woe_lau":28997199,
    "qs:woe_local":28997199,
    "qs:woe_ver":"7.10.0",
    "wof:lang":[
        "kor"
    ],
    "wof:name":"\ub2e8\ub300\ub3d9",
    "wof:placetype":"neighbourhood"
},
  "geometry": {"coordinates":[127.161255,37.450878],"type":"Point"}
}