{
  "type": "Feature",
  "properties": {
    "iso:country":"KO",
    "name:kor_x_preferred":[
        "\uc57c\ud0d11\ub3d9"
    ],
    "name:kor_x_variant":[
        "\uc57c\ud0d1",
        "\uc57c\ud0d11",
        "\uc57c\ud0d1\ub3d9"
    ],
    "name:unk_x_variant":[
        "\uc57c\ud0d11\ub3d9"
    ],
    "qs:gn_fcode":"PPL",
    "qs:gn_local":0,
    "qs:gn_namadm1":"13",
    "qs:gn_name":"Yatabi-dong",
    "qs:local_max":1671,
    "qs:local_sum":6694,
    "qs:localhoods":13,
    "qs:name":"\uc57c\ud0d11\ub3d9",
    "qs:name_adm0":"\ud55c\uad6d",
    "qs:name_adm1":"\uacbd\uae30\ub3c4",
    "qs:name_adm2":"\uc131\ub0a8\uc2dc",
    "qs:name_lau":"\ubd84\ub2f9\uad6c",
    "qs:name_local":"\ubd84\ub2f9\uad6c",
    "qs:photo_max":800,
    "qs:photo_sum":1537,
    "qs:placetype":"Suburb",
    "qs:quad_count":33,
    "qs:woe_adm0":23424868,
    "qs:woe_adm1":2345969,
    "qs:woe_adm2":28289288,
    "qs:woe_lau":28997201,
    "qs:woe_local":28997201,
    "qs:woe_ver":"7.10.0",
    "wof:lang":[
        "kor"
    ],
    "wof:name":"\uc57c\ud0d11\ub3d9",
    "wof:placetype":"neighbourhood"
},
  "geometry": {"coordinates":[127.12532899999999,37.412895],"type":"Point"}
}